CHANGELOG.txt
LICENCE.txt
MANIFEST.in
README.txt
setup.py
advancedpythonmalware/__init__.py
advancedpythonmalware.egg-info/PKG-INFO
advancedpythonmalware.egg-info/SOURCES.txt
advancedpythonmalware.egg-info/dependency_links.txt
advancedpythonmalware.egg-info/requires.txt
advancedpythonmalware.egg-info/top_level.txt