Metadata-Version: 2.1
Name: advancedpythonmalware
Version: 1.0.0
Summary: A simple library to make malware in python.
Home-page: UNKNOWN
Author: Luke Dixon
Author-email: lukeodixon@gmail.com
License: MIT
Keywords: malware
Platform: UNKNOWN
Classifier: Development Status :: 5 - Production/Stable
Classifier: Intended Audience :: Education
Classifier: Operating System :: Microsoft :: Windows :: Windows 10
Classifier: License :: OSI Approved :: MIT License
Classifier: Programming Language :: Python :: 3
License-File: LICENCE.txt
